README.rst
setup.py
nose_quickunit.egg-info/PKG-INFO
nose_quickunit.egg-info/SOURCES.txt
nose_quickunit.egg-info/dependency_links.txt
nose_quickunit.egg-info/entry_points.txt
nose_quickunit.egg-info/not-zip-safe
nose_quickunit.egg-info/requires.txt
nose_quickunit.egg-info/top_level.txt
quickunit/__init__.py
quickunit/diff.py
quickunit/plugin.py
quickunit/utils.py